[
    {
        "title": "Business Analyst - UJ",
        "company": "Dimension Data",
        "location": "Johannesburg, Gauteng, South Africa",
        "description": "Join a company that is pushing the boundaries of what is possible.",
        "link": "https://careers.services.global.ntt/global/en/job/R-117277/apply?utm_medium=phenom-feeds&utm_source=linkedin"
    },
    {
        "title": "Systems Analyst Team Leader",
        "company": "FNB South Africa",
        "location": "Johannesburg, Gauteng, South Africa",
        "description": "Are you interested to take the step? We look forward to engaging with you further",
        "link": "https://firstrand.wd3.myworkdayjobs.com/FRB/login?redirect=%2FFRB%2Fjob%2FJohannesburg%2FSystems-Analyst-Team-Leader_R16092%2Fapply%3Fsource%3DLinkedin"
    },
    {
        "title": "Functional Analyst",
        "company": "Accenture in South Africa",
        "location": "Midrand, Gauteng, South Africa",
        "description": "Are you ready to be part of a transformational journey that will reshape the digital landscape of Africa? ",
        "link": "https://www.accenture.com/za-en/careers/jobdetails?id=R00201867_en&src=LINKEDINJP"
    },
    {
        "title": "Senior Support Analyst",
        "company": "ION",
        "location": "Stellenbosch, Western Cape, South Africa",
        "description": "We are looking for an experienced professional who can manage first line of contact for clients that report application-related questions and defects involving ION Corporates enterprise software utilized in the Financial and Commodity sectors as applicable, carry significant responsibility towards managing the most complex client cases.",
        "link": "https://jobs.lever.co/ion/5359c79a-7ec9-4d07-b949-b7a8db2a3ace/apply?lever-source=Job+postings+feed&source=LinkedIn"
    }
]
